viewsets/__init__.py
viewsets/apps.py
viewsets/decorators.py
viewsets/filters.py
viewsets/mixins.py
viewsets/serializers.py
viewsets/views.py
viewsets/viewsets.py
viewsets/widgets.py
viewsets/jinja2/viewsets/base.html
viewsets/jinja2/viewsets/create.html
viewsets/jinja2/viewsets/delete.html
viewsets/jinja2/viewsets/detail.html
viewsets/jinja2/viewsets/edit.html
viewsets/jinja2/viewsets/index.html
viewsets/jinja2/viewsets/list.html
viewsets/jinja2/viewsets/popup_response.html
viewsets/jinja2/viewsets/update.html
viewsets/jinja2/viewsets/includes/_filter.html
viewsets/jinja2/viewsets/includes/_form.html
viewsets/jinja2/viewsets/includes/_form_errors.html
viewsets/jinja2/viewsets/includes/_form_field.html
viewsets/jinja2/viewsets/includes/_formset.html
viewsets/jinja2/viewsets/includes/_formset_form.html
viewsets/jinja2/viewsets/includes/_messages.html
viewsets/jinja2/viewsets/includes/_paginator.html
viewsets/jinja2/viewsets/includes/_sort_link.html
viewsets/jinja2/viewsets/widgets/lookup.html
viewsets/jinja2/viewsets/widgets/related_wrapper.html
viewsets/jinja2/viewsets/widgets/wrapper.html
viewsets/locale/en/LC_MESSAGES/django.mo
viewsets/locale/en/LC_MESSAGES/django.po
viewsets/locale/ru/LC_MESSAGES/django.mo
viewsets/locale/ru/LC_MESSAGES/django.po
viewsets/static/viewsets/css/viewsets.css
viewsets/static/viewsets/css/vendor/bootstrap.min.css
viewsets/static/viewsets/css/vendor/fontawesome.all.min.css
viewsets/static/viewsets/css/vendor/select2/select2-bootstrap4.css
viewsets/static/viewsets/css/vendor/select2/select2-bootstrap4.min.css
viewsets/static/viewsets/css/vendor/select2/select2.css
viewsets/static/viewsets/css/vendor/select2/select2.min.css
viewsets/static/viewsets/css/webfonts/fa-brands-400.eot
viewsets/static/viewsets/css/webfonts/fa-brands-400.svg
viewsets/static/viewsets/css/webfonts/fa-brands-400.ttf
viewsets/static/viewsets/css/webfonts/fa-brands-400.woff
viewsets/static/viewsets/css/webfonts/fa-brands-400.woff2
django_view_sets-0.1.7.dist-info/LICENSE
django_view_sets-0.1.7.dist-info/METADATA
django_view_sets-0.1.7.dist-info/WHEEL
django_view_sets-0.1.7.dist-info/top_level.txt
django_view_sets-0.1.7.dist-info/RECORD
